cbdcsim/__init__.py
cbdcsim/__main__.py
cbdcsim-0.1a0.dist-info/LICENSE
cbdcsim-0.1a0.dist-info/METADATA
cbdcsim-0.1a0.dist-info/WHEEL
cbdcsim-0.1a0.dist-info/entry_points.txt
cbdcsim-0.1a0.dist-info/top_level.txt
cbdcsim-0.1a0.dist-info/RECORD
