Metadata-Version: 2.1
Name: cbdcsim
Version: 0.1a0
Summary: CBCD-sim is an open source, easy-to-use, agent-based, simulator of artificial monetary transactions
Home-page: https://github.com/blackrhinoabm/CBDC-sim
Author: Joeri Schasfoort
Author-email: joeri.schasfoort@uct.ac.za
License: MIT
Download-URL: https://github.com/blackrhinoabm//CBDC-simarchive/1.0.0.tar.gz
Platform: UNKNOWN
Classifier: License :: OSI Approved :: MIT License
Classifier: Programming Language :: Python :: 3.6
Classifier: Programming Language :: Python :: 3.7
Classifier: Programming Language :: Python :: 3.8
Requires-Python: >=3.6
Requires-Dist: joblib
Requires-Dist: click
Requires-Dist: decorator
Requires-Dist: numpy
Requires-Dist: pandas
Requires-Dist: python-dateutil
Requires-Dist: pytz
Requires-Dist: scipy
Requires-Dist: threadpoolctl
Requires-Dist: xlrd
